pyhope/__init__.py
pyhope/__main__.py
pyhope/basis/__init__.py
pyhope/basis/basis_basis.py
pyhope/basis/basis_connect.py
pyhope/basis/basis_jacobian.py
pyhope/basis/basis_watertight.py
pyhope/check/__init__.py
pyhope/check/check.py
pyhope/check/check_health.py
pyhope/check/check_install.py
pyhope/common/__init__.py
pyhope/common/common.py
pyhope/common/common_numba.py
pyhope/common/common_parallel.py
pyhope/common/common_progress.py
pyhope/common/common_tools.py
pyhope/common/common_unique.py
pyhope/common/common_vars.py
pyhope/config/__init__.py
pyhope/config/config.py
pyhope/gmsh/gmsh_install.py
pyhope/gmsh/gmsh_override.py
pyhope/io/__init__.py
pyhope/io/formats/cgns.py
pyhope/io/formats/gmsh.py
pyhope/io/formats/meshio.py
pyhope/io/formats/vtk.py
pyhope/io/io.py
pyhope/io/io_debug.py
pyhope/io/io_gmsh.py
pyhope/io/io_vars.py
pyhope/io/io_xdmf.py
pyhope/mesh/__init__.py
pyhope/mesh/connect/connect.py
pyhope/mesh/connect/connect_mortar.py
pyhope/mesh/connect/connect_rbtree.py
pyhope/mesh/elements/elements_ordering.py
pyhope/mesh/elements/elements_shapefunctions.py
pyhope/mesh/fem/fem.py
pyhope/mesh/mesh.py
pyhope/mesh/mesh_builtin.py
pyhope/mesh/mesh_common.py
pyhope/mesh/mesh_duplicates.py
pyhope/mesh/mesh_external.py
pyhope/mesh/mesh_orient.py
pyhope/mesh/mesh_sides.py
pyhope/mesh/mesh_sort.py
pyhope/mesh/mesh_vars.py
pyhope/mesh/reader/reader_gambit.py
pyhope/mesh/reader/reader_gmsh.py
pyhope/mesh/reader/reader_hopr.py
pyhope/mesh/sort/sort_hilbert.py
pyhope/mesh/topology/mesh_serendipity.py
pyhope/mesh/topology/mesh_splittohex.py
pyhope/mesh/topology/mesh_topology.py
pyhope/mesh/transform/mesh_transform.py
pyhope/mesh/transform/templates/convtest.py
pyhope/mesh/transform/templates/cylinder.py
pyhope/mesh/transform/templates/default.py
pyhope/mesh/transform/templates/phill.py
pyhope/mesh/transform/templates/sphere.py
pyhope/mesh/transform/templates/sphere_box.py
pyhope/meshio/meshio_convert.py
pyhope/meshio/meshio_nodes.py
pyhope/meshio/meshio_ordering.py
pyhope-0.9.0.dist-info/METADATA
pyhope-0.9.0.dist-info/WHEEL
pyhope-0.9.0.dist-info/entry_points.txt
pyhope-0.9.0.dist-info/licenses/AUTHORS.md
pyhope-0.9.0.dist-info/licenses/LICENSE.md
pyhope-0.9.0.dist-info/RECORD
