Metadata-Version: 2.4
Name: PyHOPE
Version: 0.9.0
Summary: Python High-Order Preprocessing Environment
License: GPL-3.0-only
License-File: AUTHORS.md
License-File: LICENSE.md
Keywords: PyHOPE,mesh generator
Author: Numerics Research Group (NRG)
Author-email: numerics@iag.uni-stuttgart.de
Requires-Python: >=3.10
Classifier: Development Status :: 3 - Alpha
Classifier: Operating System :: POSIX :: Linux
Classifier: License :: OSI Approved :: GNU General Public License v3 (GPLv3)
Classifier: Programming Language :: Python :: 3
Classifier: Programming Language :: Python :: 3.10
Classifier: Programming Language :: Python :: 3.11
Classifier: Programming Language :: Python :: 3.12
Classifier: Programming Language :: Python :: 3.13
Classifier: Programming Language :: Python :: 3.14
Provides-Extra: numba
Requires-Dist: alive-progress
Requires-Dist: gmsh
Requires-Dist: h5py
Requires-Dist: hilbertcurve
Requires-Dist: meshio
Requires-Dist: numba ; extra == "numba"
Requires-Dist: numpy (>=2.0.0)
Requires-Dist: packaging
Requires-Dist: plotext
Requires-Dist: scipy
Requires-Dist: typing-extensions
Project-URL: Documentation, https://hopr-framework.github.io/PyHOPE
Project-URL: Homepage, https://numericsresearchgroup.org
Project-URL: Repository, https://github.com/hopr-framework/pyhope
